microkit_python_server_sdk/__init__.py
microkit_python_server_sdk/aes.py
microkit_python_server_sdk/conf.py
microkit_python_server_sdk/config_item.py
microkit_python_server_sdk/features_item.py
microkit_python_server_sdk/group.py
microkit_python_server_sdk/http_client.py
microkit_python_server_sdk/item.py
microkit_python_server_sdk/microkit.py
microkit_python_server_sdk/network_controller.py
microkit_python_server_sdk/notifications.py
microkit_python_server_sdk/permit.py
microkit_python_server_sdk/publisher.py
microkit_python_server_sdk/tool_builder.py
tests/__init__.py
tests/test_aes.py
tests/test_conf.py
tests/test_config_item.py
tests/test_features_item.py
tests/test_group.py
tests/test_http_client.py
tests/test_microkit.py
tests/test_microkit_notifier.py
tests/test_microkit_permit.py
tests/test_microkit_real.py
tests/test_network_controller.py
tests/test_publisher.py
microkit_python_server_sdk-1.0.1.dist-info/LICENSE
microkit_python_server_sdk-1.0.1.dist-info/METADATA
microkit_python_server_sdk-1.0.1.dist-info/WHEEL
microkit_python_server_sdk-1.0.1.dist-info/top_level.txt
microkit_python_server_sdk-1.0.1.dist-info/RECORD
