Metadata-Version: 2.1
Name: microkit_python_server_sdk
Version: 1.0.1
Summary: SDK for MicroKit framework
Author-email: Chaim Vaidberg <chaim@microkit.app>
License: Copyright (c) 2018 The Python Packaging Authority
Project-URL: Homepage, https://microkit.app
Project-URL: Documentation, https://docs.microkit.app
Classifier: Programming Language :: Python :: 3
Classifier: License :: OSI Approved :: MIT License
Classifier: Operating System :: OS Independent
Requires-Python: >=3.6
License-File: LICENSE
